OCP/__init__.py
OCP/src/Client.py
OCP/src/Commander.py
OCP/src/OCP.py
OCP/src/__init__.py
OCP/src/__main__.py
pycosmed-0.0.23.dist-info/LICENSE.txt
pycosmed-0.0.23.dist-info/METADATA
pycosmed-0.0.23.dist-info/WHEEL
pycosmed-0.0.23.dist-info/top_level.txt
pycosmed-0.0.23.dist-info/RECORD
