Metadata-Version: 2.1
Name: pycosmed
Version: 0.0.23
Summary: an OCP interface to send commands and recieve using Omnia control protocol
Home-page: https://github.com/ahmeds0s/ocp_package
Author: Ahmed M. Hesham
Author-email: ah.hesham3333@gmail.com
License: MIT
Classifier: License :: OSI Approved :: MIT License
Classifier: Operating System :: Microsoft :: Windows
Classifier: Programming Language :: Python :: 3.11
Classifier: Intended Audience :: Developers
Classifier: Intended Audience :: Science/Research
Classifier: Intended Audience :: Manufacturing
Classifier: Topic :: Software Development :: Libraries :: Python Modules
Classifier: Topic :: Scientific/Engineering :: Interface Engine/Protocol Translator
Classifier: Topic :: System :: Hardware :: Hardware Drivers
Classifier: Topic :: System :: Monitoring
Classifier: Intended Audience :: Healthcare Industry
Classifier: Topic :: Text Processing :: Markup :: XML
Classifier: Topic :: Scientific/Engineering :: Bio-Informatics
Classifier: Topic :: Scientific/Engineering :: Visualization
Requires-Python: >=3.11
License-File: LICENSE.txt
Requires-Dist: xmltodict >=0.13.0
Requires-Dist: dicttoxml2 >=2.1.0
Provides-Extra: dev
Requires-Dist: twine ; extra == 'dev'
